MANIFEST.in
README.rst
setup.py
lsm_db_extras.egg-info/PKG-INFO
lsm_db_extras.egg-info/SOURCES.txt
lsm_db_extras.egg-info/dependency_links.txt
lsm_db_extras.egg-info/requires.txt
lsm_db_extras.egg-info/top_level.txt
lsm_extras/__init__.py
lsm_extras/base.py
lsm_extras/dict.py
lsm_extras/shelves.py
lsm_extras/tree.py