Metadata-Version: 2.1
Name: lsm-db-extras
Version: 0.4.0
Summary: Thread/Process safe shelves and other lsm-db helpers
Home-page: https://github.com/mosquito/lsm-db-extras
Author: Dmitry Orlov
Author-email: me@mosquito.su
License: Apache 2
Platform: all
Classifier: License :: OSI Approved :: Apache Software License
Classifier: Topic :: Internet
Classifier: Topic :: Software Development
Classifier: Topic :: Software Development :: Libraries
Classifier: Intended Audience :: Developers
Classifier: Natural Language :: English
Classifier: Operating System :: MacOS
Classifier: Operating System :: POSIX
Classifier: Operating System :: Microsoft
Classifier: Programming Language :: Python
Classifier: Programming Language :: Python :: 3
Classifier: Programming Language :: Python :: 3.4
Classifier: Programming Language :: Python :: 3.5
Classifier: Programming Language :: Python :: 3.6
Classifier: Programming Language :: Python :: Implementation :: CPython
Provides-Extra: develop
